django_materializecss_form_bacchus-1.1.12.dist-info/DESCRIPTION.rst
django_materializecss_form_bacchus-1.1.12.dist-info/METADATA
django_materializecss_form_bacchus-1.1.12.dist-info/RECORD
django_materializecss_form_bacchus-1.1.12.dist-info/WHEEL
django_materializecss_form_bacchus-1.1.12.dist-info/metadata.json
django_materializecss_form_bacchus-1.1.12.dist-info/top_level.txt
materializecssform/__init__.py
materializecssform/config.py
materializecssform/meta.py
materializecssform/templates/materializecssform/attrs.html
materializecssform/templates/materializecssform/field.html
materializecssform/templates/materializecssform/form.html
materializecssform/templates/materializecssform/formset.html
materializecssform/templatetags/__init__.py
materializecssform/templatetags/materializecss.py
