Metadata-Version: 2.0
Name: django-materializecss-form-bacchus
Version: 1.1.12
Summary: A simple Django form template tag to work with Materializecss
Home-page: https://github.com/kalwalkden/django-materializecss-form
Author: Kal Walkden
Author-email: kal@walkden.us
License: MIT
Platform: UNKNOWN
Classifier: Programming Language :: Python
Classifier: Development Status :: 4 - Beta
Classifier: Framework :: Django
Classifier: Intended Audience :: Developers
Classifier: License :: OSI Approved :: MIT License
Classifier: Natural Language :: English
Classifier: Operating System :: OS Independent
Classifier: Programming Language :: Python :: 3.6
